basehook/__init__.py
basehook/api.py
basehook/core.py
basehook/hmac_utils.py
basehook/models.py
basehook/py.typed
basehook-0.2.0.dist-info/METADATA
basehook-0.2.0.dist-info/WHEEL
basehook-0.2.0.dist-info/top_level.txt
basehook-0.2.0.dist-info/RECORD
