Metadata-Version: 2.4
Name: basehook
Version: 0.2.0
Summary: A modern Python project
Author-email: Your Name <your.email@example.com>
License: MIT
Project-URL: Homepage, https://github.com/yourusername/basehook
Project-URL: Repository, https://github.com/yourusername/basehook
Classifier: Development Status :: 3 - Alpha
Classifier: Intended Audience :: Developers
Classifier: License :: OSI Approved :: MIT License
Classifier: Programming Language :: Python :: 3
Classifier: Programming Language :: Python :: 3.10
Classifier: Programming Language :: Python :: 3.11
Classifier: Programming Language :: Python :: 3.12
Requires-Python: >=3.10
Requires-Dist: sqlalchemy[asyncio]>=2.0
Requires-Dist: fastapi>=0.115.0
Requires-Dist: uvicorn>=0.40.0
Requires-Dist: asyncpg>=0.29.0
Provides-Extra: dev
Requires-Dist: pytest>=7.0; extra == "dev"
Requires-Dist: pytest-asyncio>=0.21.0; extra == "dev"
Requires-Dist: pytest-cov>=4.0; extra == "dev"
Requires-Dist: black>=23.0; extra == "dev"
Requires-Dist: ruff>=0.1.0; extra == "dev"
Requires-Dist: mypy>=1.0; extra == "dev"
Requires-Dist: httpx>=0.24.0; extra == "dev"
Requires-Dist: asyncpg>=0.29.0; extra == "dev"
Requires-Dist: asgi-lifespan>=2.1.0; extra == "dev"
Requires-Dist: pytest-asyncio>=1.3.0; extra == "dev"
